docs/conf.py
notctyparser/__info__.py
notctyparser/__init__.py
notctyparser/__main__.py
notctyparser/bigcty.py
notctyparser-23.6.21.dist-info/LICENSE
notctyparser-23.6.21.dist-info/METADATA
notctyparser-23.6.21.dist-info/WHEEL
notctyparser-23.6.21.dist-info/top_level.txt
notctyparser-23.6.21.dist-info/RECORD
