Metadata-Version: 2.1
Name: notctyparser
Version: 23.6.21
Summary: Just ctyparser with added version check.
Author-email: Michael Bridak <michael.bridak@gmail.com>
Project-URL: Homepage, https://github.com/mbridak/ctyparser
Project-URL: Bug Tracker, https://github.com/mbridak/ctyparser/issues
Classifier: Programming Language :: Python :: 3
Classifier: Development Status :: 5 - Production/Stable
Classifier: License :: OSI Approved :: MIT License
Classifier: Environment :: X11 Applications :: Qt
Classifier: Operating System :: POSIX :: Linux
Classifier: Intended Audience :: Developers
Classifier: Natural Language :: English
Classifier: Topic :: Communications :: Ham Radio
Requires-Python: >=3.9
License-File: LICENSE
Requires-Dist: feedparser
Requires-Dist: requests
Requires-Dist: lxml
